lnproxy/__init__.py
lnproxy/config.py
lnproxy/crypto.py
lnproxy/messages.py
lnproxy/network.py
lnproxy/onion.py
lnproxy/pk_from_hsm.py
lnproxy/private.py
lnproxy/proxy.py
lnproxy/util.py
lnproxy_core/__init__.py
lnproxy_core/config.py
lnproxy_core/crypto.py
lnproxy_core/messages.py
lnproxy_core/network.py
lnproxy_core/onion.py
lnproxy_core/pk_from_hsm.py
lnproxy_core/private.py
lnproxy_core/proxy.py
lnproxy_core/util.py
lnproxy_core/version.py
lnproxy-0.3.6.dist-info/LICENSE
lnproxy-0.3.6.dist-info/METADATA
lnproxy-0.3.6.dist-info/WHEEL
lnproxy-0.3.6.dist-info/top_level.txt
lnproxy-0.3.6.dist-info/RECORD
