Metadata-Version: 2.1
Name: lnproxy
Version: 0.3.6
Summary: A C-Lightning transport proxy
Home-page: https://github.com/willcl-ark/lnproxy
Author: Will Clark
Author-email: will8clark@gmail.com
License: UNKNOWN
Platform: UNKNOWN
Classifier: Programming Language :: Python :: 3
Classifier: License :: OSI Approved :: MIT License
Classifier: Operating System :: OS Independent
Requires-Python: >=3.7
Requires-Dist: trio (>=0.13.0)
Requires-Dist: pyln.client (>=0.8.0)
Requires-Dist: hkdf (>=0.0.3)
Requires-Dist: coincurve (>=13.0.0)
Requires-Dist: eciespy (>=0.3.5)
